privacy/qa/commons/__init__.py
privacy.qa.commons-0.0.1.dist-info/METADATA
privacy.qa.commons-0.0.1.dist-info/WHEEL
privacy.qa.commons-0.0.1.dist-info/top_level.txt
privacy.qa.commons-0.0.1.dist-info/RECORD
